opentele/__init__.py
opentele/api.py
opentele/debug.py
opentele/devices.py
opentele/exception.py
opentele/utils.py
opentele/td/__init__.py
opentele/td/account.py
opentele/td/auth.py
opentele/td/configs.py
opentele/td/mtp.py
opentele/td/shared.py
opentele/td/storage.py
opentele/td/tdesktop.py
opentele/tl/__init__.py
opentele/tl/configs.py
opentele/tl/shared.py
opentele/tl/telethon.py
opentele-1.15.1.dist-info/LICENSE
opentele-1.15.1.dist-info/METADATA
opentele-1.15.1.dist-info/WHEEL
opentele-1.15.1.dist-info/top_level.txt
opentele-1.15.1.dist-info/RECORD
