Metadata-Version: 2.1
Name: opentele
Version: 1.15.1
Summary: A Python Telegram API Library for converting between tdata and telethon sessions, with built-in official Telegram APIs.
Home-page: https://github.com/thedemons/opentele
Author: thedemons
Author-email: thedemons@gmail.com
License: MIT
Keywords: tdata,tdesktop,telegram,telethon,opentele
Platform: UNKNOWN
Classifier: License :: OSI Approved :: MIT License
Classifier: Operating System :: Microsoft :: Windows
Classifier: Operating System :: MacOS
Classifier: Operating System :: POSIX :: Linux
Classifier: Programming Language :: Python :: 3
Classifier: Programming Language :: Python :: 3.7
Classifier: Development Status :: 5 - Production/Stable
